README.md
setup.cfg
setup.py
abhishek_k/Binomialdistribution.py
abhishek_k/Gaussiandistribution.py
abhishek_k/Generaldistribution.py
abhishek_k/__init__.py
abhishek_k.egg-info/PKG-INFO
abhishek_k.egg-info/SOURCES.txt
abhishek_k.egg-info/dependency_links.txt
abhishek_k.egg-info/not-zip-safe
abhishek_k.egg-info/top_level.txt